{
    "volume": "018",
    "issue": "07",
    "year": "2017",
    "month": "07",
    "theme": "",
    "id": "018/07",
    "toc": [
        {
            "title": "ಮನೀಷಾ ಪಂಚಕಮ್-೧",
            "feature": "ಪ್ರಾರ್ಥನೆ",
            "text": "",
            "page": "0006-0006",
            "relativePageNumber": 1,
            "fullText": [

            ]
        },
        {
            "title": "ಬೆಳಕ ಬೀರುವ ಹಾದಿ-೨",
            "feature": "ಸಂಪಾದಕೀಯ",
            "text": "",
            "page": "0009-0011",
            "relativePageNumber": 1,
            "fullText": [

            ]
        },
        {
            "title": "ಸಾಧು ಜೀವನ",
            "feature": "ಶ್ರೀರಾಮಕೃಷ್ಣ ವಚನವೇದದಿಂದ",
            "text": "",
            "page": "0012-0012",
            "relativePageNumber": 1,
            "fullText": [

            ]
        },
        {
            "title": "ಅಘೋರಮಣಿ ದೇವಿ",
            "feature": "ವಿಶೇಷ ಲೇಖನ",
            "text": "",
            "page": "0013-0016",
            "relativePageNumber": 1,
            "fullText": [

            ],
            "author": [
                {
                    "name": "ಅನುರಾಧಾ ವಸಂತಕುಮಾರ್",
                    "salutation": ""
                }
            ]
        },
        {
            "title": "ಶ್ರೀಮಾತೆ ಭಾಗ-೭",
            "feature": "ಧಾರಾವಾಹಿ",
            "text": "",
            "page": "0017-0020",
            "relativePageNumber": 1,
            "fullText": [

            ],
            "author": [
                {
                    "name": "ಆಶುತೋಷ್ ಮಿತ್ರ",
                    "salutation": ""
                }
            ]
        },
        {
            "title": "ನಿವೇದಿತಾ‌ ಕಲಿಸುವಂತೆ `ರಾಷ್ಟ್ರೀಯ ಶಿಕ್ಷಣ'",
            "feature": "ವಿಶೇಷ ಲೇಖನ",
            "text": "",
            "page": "0021-0025",
            "relativePageNumber": 1,
            "fullText": [

            ],
            "author": [
                {
                    "name": "ಎಸ್. ಕೆ. ಚಕ್ರವರ್ತಿ",
                    "salutation": ""
                }
            ]
        },
        {
            "title": "ಯಶೋದಾ ಮಯಿ `ವೈಷ್ಣವ ಮೇರಿ'",
            "feature": "ವಿಶೇಷ ಲೇಖನ",
            "text": "",
            "page": "0026-0027",
            "relativePageNumber": 1,
            "fullText": [

            ],
            "author": [
                {
                    "name": "ಸ್ವರ್ಣಗೌರಿ",
                    "salutation": ""
                }
            ]
        },
        {
            "title": "ಶ್ರೀಮಾತೆಯವರ ಪತ್ರಗಳು-೪",
            "feature": "ವಿಶೇಷ ಲೇಖನ",
            "text": "",
            "page": "0028-0029",
            "relativePageNumber": 1,
            "fullText": [

            ]
        },
        {
            "title": "ಕಳೆದ ದಿನಗಳ ನೆನಪುಗಳು-೮",
            "feature": "ಧಾರಾವಾಹಿ",
            "text": "",
            "page": "0030-0033",
            "relativePageNumber": 1,
            "fullText": [

            ],
            "author": [
                {
                    "name": "ಶ್ರದ್ಧಾನಂದ",
                    "salutation": "ಸ್ವಾಮಿ"
                }
            ]
        },
        {
            "title": "ಸುಮಧುರ ಶೈಲಿಯ ರಾಮಾಯಣ ಕೃತಿ",
            "feature": "ಪುಸ್ತಕ ಪರಿಚಯ",
            "text": "",
            "page": "0034-0034",
            "relativePageNumber": 1,
            "fullText": [

            ]
        },
        {
            "title": "ಕೃಷ್ಣ ಸಖ ಸಂತ ನರಸೀ ಮೆಹ್ತಾ",
            "feature": "ಸಂತರ ಜೀವನ",
            "text": "",
            "page": "0035-0037",
            "relativePageNumber": 1,
            "fullText": [

            ],
            "author": [
                {
                    "name": "ವೀರೇಶಾನಂದ",
                    "salutation": "ಸ್ವಾಮಿ"
                }
            ]
        },
        {
            "title": "ತ್ರ್ಯಂಬಕೇಶ್ವರದ ಜ್ಯೋತಿರ್ಲಿಂಗ",
            "feature": "ಚಿತ್ರಕಥೆ",
            "text": "",
            "page": "0038-0041",
            "relativePageNumber": 1,
            "fullText": [

            ]
        },
        {
            "title": "ಸುದ್ದಿಸಂಚಯ",
            "feature": "",
            "text": "",
            "page": "0042-0044",
            "relativePageNumber": 1,
            "fullText": [

            ]
        }
    ]
}