{
    "volume": "011",
    "issue": "08",
    "year": "2010",
    "month": "08",
    "theme": "",
    "id": "011/08",
    "toc": [
        {
            "title": "ಪ್ರಾರ್ಥನೆ",
            "feature": "ಪ್ರಾರ್ಥನೆ",
            "page": "0005-0005",
            "relativePageNumber": 3,
            "fullText": [
                {
                    "page": "0005",
                    "text": ""
                }
            ],
            "author": [
                {
                    "name": "ಸಂಪಾದಕರು",
                    "salutation": ""
                }
            ]
        },
        {
            "title": "ಸ್ಮರಣೆ ಒಂದೇ ಸಾಲದೆ ಗೋವಿಂದನ",
            "feature": "ಸಂಪಾದಕರು",
            "page": "0007-0010",
            "relativePageNumber": 5,
            "fullText": [
                {
                    "page": "0007",
                    "text": ""
                },
                {
                    "page": "0008",
                    "text": ""
                },
                {
                    "page": "0009",
                    "text": ""
                },
                {
                    "page": "0010",
                    "text": ""
                }
            ],
            "author": [
                {
                    "name": "ಸಂಪಾದಕರು",
                    "salutation": ""
                }
            ]
        },
        {
            "title": "ವೇದಾಂತ ಮತ್ತು ರಾಮಕೃಷ್ಣ-ವಿವೇಕಾನಂದ ಭಾವಧಾರೆ",
            "feature": "",
            "page": "0011-0012",
            "relativePageNumber": 9,
            "fullText": [
                {
                    "page": "0011",
                    "text": ""
                },
                {
                    "page": "0012",
                    "text": ""
                }
            ],
            "author": [
                {
                    "name": "ನಿತ್ಯಸ್ಥಾನಂದ",
                    "salutation": "ಸ್ವಾಮಿ"
                }
            ]
        },
        {
            "title": "ದರಿದ್ರದೇವೋ ಭವ",
            "feature": "",
            "page": "0013-0014",
            "relativePageNumber": 11,
            "fullText": [
                {
                    "page": "0013",
                    "text": ""
                },
                {
                    "page": "0014",
                    "text": ""
                }
            ],
            "author": [
                {
                    "name": "ವಿಜಯಕುಮಾರ",
                    "salutation": ""
                }
            ]
        },
        {
            "title": "ಸ್ನೇಹಪ್ರಭ",
            "feature": "",
            "page": "0015-0015",
            "relativePageNumber": 13,
            "fullText": [
                {
                    "page": "0015",
                    "text": ""
                }
            ]
        },
        {
            "title": "ಆದ್ಯತೆಗಳಿಂದ ವಿಮುಖವಾದ ಆರ್ಥಿಕ ಕಲಾಪಗಳು",
            "feature": "",
            "page": "0016-0018",
            "relativePageNumber": 14,
            "fullText": [
                {
                    "page": "0016",
                    "text": ""
                },
                {
                    "page": "0017",
                    "text": ""
                },
                {
                    "page": "0018",
                    "text": ""
                }
            ],
            "author": [
                {
                    "name": "ರಾಮಸ್ವಾಮಿ ಎಸ್. ಆರ್.",
                    "salutation": ""
                }
            ]
        },
        {
            "title": "ಬಡತನ ನಿರ್ಮೂಲನೆ: ಗಾಂಧೀ ಪರಿಹಾರ",
            "feature": "",
            "page": "0019-0021",
            "relativePageNumber": 17,
            "fullText": [
                {
                    "page": "0019",
                    "text": ""
                },
                {
                    "page": "0020",
                    "text": ""
                },
                {
                    "page": "0021",
                    "text": ""
                }
            ],
            "author": [
                {
                    "name": "ಸುರೇಂದ್ರ ಕೌಲಗಿ",
                    "salutation": ""
                }
            ]
        },
        {
            "title": "ಬಡತನ ಒಂದು ವಿಶ್ಲೇಷಣೆ",
            "feature": "",
            "page": "0022-0024",
            "relativePageNumber": 20,
            "fullText": [
                {
                    "page": "0022",
                    "text": ""
                },
                {
                    "page": "0023",
                    "text": ""
                },
                {
                    "page": "0024",
                    "text": ""
                }
            ],
            "author": [
                {
                    "name": "ಜಯದೇವ ಜಿ. ಎಸ್.",
                    "salutation": ""
                }
            ]
        },
        {
            "title": "ಆತ್ಮಹತ್ಯೆಗಳು ಕಾಡುವುದು ಸತ್ತವರನ್ನಲ್ಲ, ಬದುಕಿರುವವರನ್ನು",
            "feature": "",
            "page": "0025-0026",
            "relativePageNumber": 23,
            "fullText": [
                {
                    "page": "0025",
                    "text": ""
                },
                {
                    "page": "0026",
                    "text": ""
                }
            ],
            "author": [
                {
                    "name": "ಸಾಯಿನಾಥ್",
                    "salutation": ""
                }
            ]
        },
        {
            "title": "ಪುಸ್ತಕಲೋಕ",
            "feature": "",
            "page": "0027-0029",
            "relativePageNumber": 25,
            "fullText": [
                {
                    "page": "0027",
                    "text": ""
                },
                {
                    "page": "0028",
                    "text": ""
                },
                {
                    "page": "0029",
                    "text": ""
                }
            ]
        },
        {
            "title": "ವಾರ್ತಾ ವಿಶ್ಲೇಷಣೆ",
            "feature": "ವಾರ್ತಾವಿಶ್ಲೇಷಣೆ",
            "page": "0029-0029",
            "relativePageNumber": 27,
            "fullText": [
                {
                    "page": "0029",
                    "text": ""
                }
            ]
        },
        {
            "title": "ಸ್ವಾಮಿ ಭೂತೇಶಾನಂದಜಿ ಅವರ ಸವಿನೆನಪುಗಳು",
            "feature": "",
            "page": "0030-0032",
            "relativePageNumber": 28,
            "fullText": [
                {
                    "page": "0030",
                    "text": ""
                },
                {
                    "page": "0031",
                    "text": ""
                },
                {
                    "page": "0032",
                    "text": ""
                }
            ]
        },
        {
            "title": "ಸ್ವಾಮಿ ವಿವೇಕಾನಂದರ ಕೃತಿಶ್ರೇಣಿಯಿಂದ",
            "feature": "",
            "page": "0033-0033",
            "relativePageNumber": 31,
            "fullText": [
                {
                    "page": "0033",
                    "text": ""
                }
            ]
        },
        {
            "title": "ಬನ್ನಿ, ಬೇಲೂರು ಮಠಕ್ಕೆ",
            "feature": "",
            "page": "0034-0035",
            "relativePageNumber": 32,
            "fullText": [
                {
                    "page": "0034",
                    "text": ""
                },
                {
                    "page": "0035",
                    "text": ""
                }
            ],
            "author": [
                {
                    "name": "ಆಶುತೋಷಾನಂದ",
                    "salutation": "ಸ್ವಾಮಿ"
                }
            ]
        },
        {
            "title": "ನಿಮ್ಮ ಮೂರು ಶರೀರಗಳನ್ನೂ ಪವಿತ್ರಗೊಳಿಸಿಕೊಳ್ಳಿ",
            "feature": "",
            "page": "0036-0038",
            "relativePageNumber": 34,
            "fullText": [
                {
                    "page": "0036",
                    "text": ""
                },
                {
                    "page": "0037",
                    "text": ""
                },
                {
                    "page": "0038",
                    "text": ""
                }
            ]
        },
        {
            "title": "ಓದುವುದು ಹೇಗೆ?",
            "feature": "",
            "page": "0039-0039",
            "relativePageNumber": 37,
            "fullText": [
                {
                    "page": "0039",
                    "text": ""
                }
            ]
        },
        {
            "title": "ಕಥೋಪದೇಶ",
            "feature": "ಕಥೋಪದೇಶ",
            "page": "0040-0041",
            "relativePageNumber": 38,
            "fullText": [
                {
                    "page": "0040",
                    "text": ""
                },
                {
                    "page": "0041",
                    "text": ""
                }
            ]
        },
        {
            "title": "ಸುದ್ದಿ ಸಂಚಯ",
            "feature": "ಸುದ್ದಿಸಂಚಯ",
            "page": "0042-0042",
            "relativePageNumber": 40,
            "fullText": [
                {
                    "page": "0042",
                    "text": ""
                }
            ]
        }
    ]
}