{
    "volume": "012",
    "issue": "02",
    "year": "2011",
    "month": "02",
    "theme": "",
    "id": "012/02",
    "toc": [
        {
            "title": "ಸೂಕ್ತಿಪ್ರಭ",
            "feature": "ಪ್ರಾರ್ಥನೆ",
            "page": "0005-0005",
            "fullText": [
                {
                    "page": "0005",
                    "text": ""
                }
            ],
            "relativePageNumber": 2
        },
        {
            "title": "ಮನಃಶಾಸ್ತ್ರಜ್ಞರಾಗಿ ಸ್ವಾಮಿ ವಿವೇಕಾನಂದರು",
            "feature": "ಸಂಪಾದಕೀಯ",
            "page": "0007-0010",
            "fullText": [
                {
                    "page": "0007",
                    "text": ""
                },
                {
                    "page": "0008",
                    "text": ""
                },
                {
                    "page": "0009",
                    "text": ""
                },
                {
                    "page": "0010",
                    "text": ""
                }
            ],
            "relativePageNumber": 4
        },
        {
            "title": "ಜ್ಞಾನಯೋಗದ ತತ್ತ್ವವಿಚಾರ",
            "feature": "",
            "page": "0011-0014",
            "fullText": [
                {
                    "page": "0011",
                    "text": ""
                },
                {
                    "page": "0012",
                    "text": ""
                },
                {
                    "page": "0013",
                    "text": ""
                },
                {
                    "page": "0014",
                    "text": ""
                }
            ],
            "relativePageNumber": 8,
            "author": [
                {
                    "name": "ಸೋಮನಾಥಾನಂದ",
                    "salutation": "ಸ್ವಾಮಿ "
                }
            ]
        },
        {
            "title": "ಸ್ವಾಮಿ ವಿವೇಕಾನಂದರ 'ಭಕ್ತಿಯೋಗ'",
            "feature": "",
            "page": "0015-0018",
            "fullText": [
                {
                    "page": "0015",
                    "text": ""
                },
                {
                    "page": "0016",
                    "text": ""
                },
                {
                    "page": "0017",
                    "text": ""
                },
                {
                    "page": "0018",
                    "text": ""
                }
            ],
            "relativePageNumber": 12,
            "author": [
                {
                    "name": "ತ್ರಿಲೋಕಾತ್ಮಾನಂದ",
                    "salutation": "ಸ್ವಾಮಿ"
                }
            ]
        },
        {
            "title": "ಸ್ವಾಮಿ ವಿವೇಕಾನಂದರ 'ಕರ್ಮಯೋಗ'",
            "feature": "",
            "page": "0019-0022",
            "fullText": [
                {
                    "page": "0019",
                    "text": ""
                },
                {
                    "page": "0020",
                    "text": ""
                },
                {
                    "page": "0021",
                    "text": ""
                },
                {
                    "page": "0022",
                    "text": ""
                }
            ],
            "relativePageNumber": 16,
            "author": [
                {
                    "name": "ಬ್ರಹ್ಮಚಾರಿ ಸುವಿಮಲಚೈತನ್ಯ",
                    "salutation": ""
                }
            ]
        },
        {
            "title": "ಶ್ರೀಮಾತೆ ಮತ್ತು ಆಧುನಿಕ ಮಹಿಳೆ",
            "feature": "",
            "page": "0023-0026",
            "fullText": [
                {
                    "page": "0023",
                    "text": ""
                },
                {
                    "page": "0024",
                    "text": ""
                },
                {
                    "page": "0025",
                    "text": ""
                },
                {
                    "page": "0026",
                    "text": ""
                }
            ],
            "relativePageNumber": 20,
            "author": [
                {
                    "name": "ಅಮಲಪ್ರಾಣಾ",
                    "salutation": "ಪ್ರವ್ರಾಜಿಕಾ"
                }
            ]
        },
        {
            "title": "ಸ್ವಾಮಿ ವಿವೇಕಾನಂದರ ಮಹಾನತೆ",
            "feature": "",
            "page": "0027-0028",
            "fullText": [
                {
                    "page": "0027",
                    "text": ""
                },
                {
                    "page": "0028",
                    "text": ""
                }
            ],
            "relativePageNumber": 24,
            "author": [
                {
                    "name": "ಡಿ.ವಿ.ಜಿ.",
                    "salutation": ""
                }
            ]
        },
        {
            "title": "ಶ್ರೀಮಾತೆಯವರ ದಾಕ್ಷಿಣಾತ್ಯ ಶಿಷ್ಯರು",
            "feature": "",
            "page": "0029-0031",
            "fullText": [
                {
                    "page": "0029",
                    "text": ""
                },
                {
                    "page": "0030",
                    "text": ""
                },
                {
                    "page": "0031",
                    "text": ""
                }
            ],
            "relativePageNumber": 26,
            "author": [
                {
                    "name": "ಭವಾನಿಪ್ರಾಣಾ",
                    "salutation": "ಪ್ರವ್ರಾಜಿಕಾ"
                }
            ]
        },
        {
            "title": "ಆಚಾರ್ಯತ್ರಯರು",
            "feature": "",
            "page": "0032-0033",
            "fullText": [
                {
                    "page": "0032",
                    "text": ""
                },
                {
                    "page": "0033",
                    "text": ""
                }
            ],
            "relativePageNumber": 29,
            "author": [
                {
                    "name": "ಎಚ್. ವಿ. ಸರೋಜ",
                    "salutation": ""
                }
            ]
        },
        {
            "title": "ನಾ ಕಂಡಂತೆ ಸ್ವಾಮೀಜಿ",
            "feature": "ದಿವ್ಯಸ್ಮೃತಿಪ್ರಭ",
            "page": "0034-0037",
            "fullText": [
                {
                    "page": "0034",
                    "text": ""
                },
                {
                    "page": "0035",
                    "text": ""
                },
                {
                    "page": "0036",
                    "text": ""
                },
                {
                    "page": "0037",
                    "text": ""
                }
            ],
            "relativePageNumber": 31,
            "author": [
                {
                    "name": "ಅಖಂಡಾನಂದ",
                    "salutation": "ಸ್ವಾಮಿ"
                }
            ]
        },
        {
            "title": "ಬನ್ನಿ, ದಕ್ಷಿಣೇಶ್ವರಕ್ಕೆ",
            "feature": "",
            "page": "0038-0039",
            "fullText": [
                {
                    "page": "0038",
                    "text": ""
                },
                {
                    "page": "0039",
                    "text": ""
                }
            ],
            "relativePageNumber": 35,
            "author": [
                {
                    "name": "ಆಶುತೋಷಾನಂದ",
                    "salutation": "ಸ್ವಾಮಿ "
                }
            ]
        },
        {
            "title": "ಪರೀಕ್ಷೆ,ಪರೀಕ್ಷೆ,ಪರೀಕ್ಷೆ,...",
            "feature": "ವಿದ್ಯಾರ್ಥಿಪ್ರಭ",
            "page": "0040-0041",
            "fullText": [
                {
                    "page": "0040",
                    "text": ""
                },
                {
                    "page": "0041",
                    "text": ""
                }
            ],
            "relativePageNumber": 37
        },
        {
            "title": "ಸುದ್ದಿ ಸಂಚಯ",
            "feature": "",
            "page": "0042-0042",
            "fullText": [
                {
                    "page": "0042",
                    "text": ""
                }
            ],
            "relativePageNumber": 39
        }
    ]
}