{
    "volume": "016",
    "issue": "12",
    "year": "2015",
    "month": "12",
    "theme": "",
    "id": "016/12",
    "toc": [
        {
            "title": "ಪ್ರಾರ್ಥನೆ: ಶ್ರೀಶಾರದಾದೇವ್ಯಷ್ಟಕದಿಂದ ಸೂಕ್ತಿಪ್ರಭ: ಶ್ರೀಮಾತೆಯವರ ಉಪದೇಶಾವಳಿ",
            "feature": "ಪ್ರಾರ್ಥನೆ",
            "page": "0004-0004",
            "relativePageNumber": 2,
            "relativePageRange": "2-2",
            "fullText": [
                {
                    "page": "0004",
                    "text": ""
                }
            ]
        },
        {
            "title": "ಭಾವನಿರ್ಭರ ಭಕ್ತಿ",
            "feature": "ಸಂಪಾದಕೀಯ",
            "page": "0007-0010",
            "relativePageNumber": 5,
            "relativePageRange": "5-8",
            "fullText": [
                {
                    "page": "0007",
                    "text": ""
                },
                {
                    "page": "0008",
                    "text": ""
                },
                {
                    "page": "0009",
                    "text": ""
                },
                {
                    "page": "0010",
                    "text": ""
                }
            ]
        },
        {
            "title": "ಏಕಾಂತವಾಸ",
            "feature": "ಶ್ರೀರಾಮಕೃಷ್ಣ ವಚನವೇದದಿಂದ",
            "page": "0011-0011",
            "relativePageNumber": 9,
            "relativePageRange": "9-9",
            "fullText": [
                {
                    "page": "0011",
                    "text": ""
                }
            ]
        },
        {
            "title": "ಶ್ರೀಮಾತೆಯವರು:ಸ್ವಾಮಿ ಬ್ರಹ್ಮಾನಂದರ ದೃಷ್ಟಿಯಲ್ಲಿ",
            "feature": "ಶ್ರೀಮಾತೆಯವರು",
            "page": "0012-0016",
            "relativePageNumber": 10,
            "relativePageRange": "10-14",
            "fullText": [
                {
                    "page": "0012",
                    "text": ""
                },
                {
                    "page": "0013",
                    "text": ""
                },
                {
                    "page": "0014",
                    "text": ""
                },
                {
                    "page": "0015",
                    "text": ""
                },
                {
                    "page": "0016",
                    "text": ""
                }
            ],
            "author": [
                {
                    "name": "ಪೂರ್ಣಾತ್ಮಾನಂದ",
                    "salutation": "ಸ್ವಾಮಿ"
                }
            ]
        },
        {
            "title": "ಅಮ್ಮನಿಗೊಂದು ಪತ್ರ",
            "feature": "ಶ್ರೀಮಾತೆಯವರು",
            "page": "0017-0018",
            "relativePageNumber": 15,
            "relativePageRange": "15-16",
            "fullText": [
                {
                    "page": "0017",
                    "text": ""
                },
                {
                    "page": "0018",
                    "text": ""
                }
            ],
            "author": [
                {
                    "name": "ಸದಾಶಿವ ಹಿರೇಮಠ",
                    "salutation": ""
                }
            ]
        },
        {
            "title": "ಸ್ವಾಮಿ ಅಖಂಡಾನಂದರ ಸ್ಮೃತಿಸಂಚಯ - ಭಾಗ ೧೪",
            "feature": "ಧಾರಾವಾಹಿ",
            "page": "0019-0023",
            "relativePageNumber": 17,
            "relativePageRange": "17-21",
            "fullText": [
                {
                    "page": "0019",
                    "text": ""
                },
                {
                    "page": "0020",
                    "text": ""
                },
                {
                    "page": "0021",
                    "text": ""
                },
                {
                    "page": "0022",
                    "text": ""
                },
                {
                    "page": "0023",
                    "text": ""
                }
            ],
            "author": [
                {
                    "name": "ನಿರಾಮಯಾನಂದ",
                    "salutation": "ಸ್ವಾಮಿ"
                }
            ]
        },
        {
            "title": "ಮಾಯೆಯೊಳಗೆ ಮಹಾಮಾಯೆ",
            "feature": "ಶ್ರೀಮಾತೆಯವರು",
            "page": "0024-0026",
            "relativePageNumber": 22,
            "relativePageRange": "22-24",
            "fullText": [
                {
                    "page": "0024",
                    "text": ""
                },
                {
                    "page": "0025",
                    "text": ""
                },
                {
                    "page": "0026",
                    "text": ""
                }
            ],
            "author": [
                {
                    "name": "ಪ್ರವ್ರಾಜಿಕಾ ಧರ್ಮಪ್ರಾಣಾ",
                    "salutation": ""
                }
            ]
        },
        {
            "title": "ಒರಟ ಸಂನ್ಯಾಸಿ ಹಾಗೂ ಶ್ರೀಮಾತೆ",
            "feature": "ಶ್ರೀಮಾತೆಯವರು",
            "page": "0027-0028",
            "relativePageNumber": 25,
            "relativePageRange": "25-26",
            "fullText": [
                {
                    "page": "0027",
                    "text": ""
                },
                {
                    "page": "0028",
                    "text": ""
                }
            ],
            "author": [
                {
                    "name": "ಶಾಂತಾನಂದ ಪುರಿ",
                    "salutation": "ಸ್ವಾಮಿ"
                }
            ]
        },
        {
            "title": "ಶ್ರೀಮಾತೆಯವರ ಕೃಪೆ - ಬಾಗ ೧",
            "feature": "ಶ್ರೀಮಾತೆಯವರು",
            "page": "0029-0034",
            "relativePageNumber": 27,
            "relativePageRange": "27-32",
            "fullText": [
                {
                    "page": "0029",
                    "text": ""
                },
                {
                    "page": "0030",
                    "text": ""
                },
                {
                    "page": "0031",
                    "text": ""
                },
                {
                    "page": "0032",
                    "text": ""
                },
                {
                    "page": "0033",
                    "text": ""
                },
                {
                    "page": "0034",
                    "text": ""
                }
            ],
            "author": [
                {
                    "name": "ಅಪೂರ್ವಾನಂದ",
                    "salutation": "ಸ್ವಾಮಿ"
                }
            ]
        },
        {
            "title": "ರಾಜಾ ಜನಕನ ಕಥೆ",
            "feature": "ಯೋಗವಾಸಿಷ್ಠದ ಕಥೆಗಳು",
            "page": "0035-0037",
            "relativePageNumber": 33,
            "relativePageRange": "33-35",
            "fullText": [
                {
                    "page": "0035",
                    "text": ""
                },
                {
                    "page": "0036",
                    "text": ""
                },
                {
                    "page": "0037",
                    "text": ""
                }
            ],
            "author": [
                {
                    "name": "ವೀರೇಶಾನಂದ",
                    "salutation": "ಸ್ವಾಮಿ"
                }
            ]
        },
        {
            "title": "ಅಷ್ಟಾವಕ್ರ ಗೀತೆಯ ಉಗಮ",
            "feature": "ಚಿತ್ರಕಥೆ",
            "page": "0038-0041",
            "relativePageNumber": 36,
            "relativePageRange": "36-39",
            "fullText": [
                {
                    "page": "0038",
                    "text": ""
                },
                {
                    "page": "0039",
                    "text": ""
                },
                {
                    "page": "0040",
                    "text": ""
                },
                {
                    "page": "0041",
                    "text": ""
                }
            ]
        },
        {
            "title": "ಸುದ್ದಿ ಸಂಚಯ",
            "feature": "",
            "page": "0042-0042",
            "relativePageNumber": 40,
            "relativePageRange": "40-40",
            "fullText": [
                {
                    "page": "0042",
                    "text": ""
                }
            ]
        }
    ]
}