{
    "volume": "017",
    "issue": "09",
    "month": "09",
    "year": "2016",
    "theme": "",
    "id": "017/09",
    "toc": [
        {
            "title": "ಪ್ರಾರ್ಥನೆ: ಶ್ರೀ ಗೋವಿಂದಾಷ್ಟಕಮ್ - 2",
            "feature": "ಪ್ರಾರ್ಥನೆ",
            "text": "",
            "page": "0004-0004"
        },
        {
            "title": "ಮಾತು-ಮೌನದ ನಡುವೆ",
            "feature": "ಸಂಪಾದಕೀಯ",
            "text": "",
            "page": "0007-0009"
        },
        {
            "title": "ಹೆತ್ತ ತಾಯಿ",
            "feature": "ಶ್ರೀರಾಮಕೃಷ್ಣ ವಚನವೇದದಿಂದ",
            "text": "ಏನು, ಹೆತ್ತ ತಾಯಿ ಕಸಕಡ್ಡಯೆ! ಎಷ್ಟೊಂದು ತನ್ನ ತಾಯಿಗೆ",
            "page": "0010-0010"
        },
        {
            "title": "ಸಮಗ್ರ ಶಿಕ್ಷಣದ ತತ್ತ್ವ ಗಳು ಮತ್ತು ಗುರಿಗಳು: ಶ್ರೀ ಅರವಿಂದರ ವಿಚಾರಧಾರೆ",
            "feature": "ವಿಶೇಷ ಲೇಖನ",
            "text": "ಒಬ್ಬ ಮಹಾಯೋಗಿಯಾಗಿ, ಅಪ್ರತಿಮ ದಾರ್ಶನಿಕ  ಕವಿಯಾಗಿ ಮತ್ತು ಅಸಾಧಾರಣ",
            "page": "0011-0013",
            "author": [
                {
                    "name": "ಸರಗೂರು ರಮೇಶ್",
                    "salutation": ""
                }
            ]
        },
        {
            "title": "ಅನ್ಯಥಾ ಶರಣಂ ನಾಸ್ತಿ..' - (ಶರಣಾಗತಿಯ ವೈಭವ) ಭಾಗ-೨",
            "feature": "ವಿಶೇಷ ಲೇಖನ",
            "text": "ಷಡ್ವಿಧಗಳ ಶರಣಾಗತಿಯಲ್ಲಿ ಆರನೆಯದು ಹಾಗೂ ಕೊನೆಯದು",
            "page": "0014-0018",
            "author": [
                {
                    "name": "ಶಶಿಕಲಾ ಶ್ರೀಧರ್",
                    "salutation": ""
                }
            ]
        },
        {
            "title": "ಶ್ರೀಕೃಷ್ಣನ ಲೀಲಾತಾಣ ಗೋವರ್ಧನ",
            "feature": "ವಿಶೇಷ ಲೇಖನ",
            "text": "ಸ್ವಾಮಿ ವಿವೇಕಾನಂದರು ಪಾಶ್ಚಾತ್ಯ ದೇಶಗಳಲ್ಲಿ ಹಲವಾರು ವರ್ಷಗಳಿದ್ದು  ಹಿಂತಿರುಗಿ",
            "page": "0020-0023",
            "author": [
                {
                    "name": "ಕೆ.ಎಲ್. ಪ್ರಸನ್ನಾಕ್ಷೀ",
                    "salutation": "ಡಾ"
                }
            ]
        },
        {
            "title": "ಅನಾರೋಗ್ಯದ ಆಸರೆ!",
            "feature": "ವಿಶೇಷ ಲೇಖನ",
            "text": "ನಾವೆಲ್ಲರೂ ಆರೋಗ್ಯ ಪೂರ್ಣ ಜೀವನವನ್ನು ಇಷ್ಟಪಡುತ್ತೇವೆ",
            "page": "0024-0026",
            "author": [
                {
                    "name": "ಡಿ.ಎಂ. ಹೆಗಡೆ",
                    "salutation": ""
                }
            ]
        },
        {
            "title": "ಅಪರೂಪದ ಯೋಗಿ - ಅಥಣಿ ಶಿವಯೋಗಿ",
            "feature": "ವಿಶೇಷ ಲೇಖನ",
            "text": "ಸಪ್ತಗ್ರಾಮ ಮತ್ತು ಇಂಗಳಗಾವಿ ಅಕ್ಕಪಕ್ಕದ ಹಳ್ಳಿ ಗಳು",
            "page": "0027-0030",
            "author": [
                {
                    "name": "ಸದಾನಂದ ಕನಹಳ್ಳಿ ",
                    "salutation": "ಪ್ರೊ"
                }
            ]
        },
        {
            "title": "ಕಾಗೆ ಬಣ್ಣವೇಕೆ ಕಪ್ಪು ಮತ್ತು ಗೂಬೆ ಏಕೆ ನಿಶಾಚರ",
            "feature": "ಜಪಾನಿನ ಕಥೆಗಳು",
            "text": "ಒಂದು ಸಮಯದಲ್ಲಿ ಕಾಗೆಯೂ ಬೆಳ್ಳಗೇ ಇತ್ತು ಎಂದು ನಮ್ಮಲ್ಲಿ",
            "page": "0031-0031"
        },
        {
            "title": "`ತಮಸೋಮಾ ಜ್ಯೋತಿರ್ಗಮಯ', `ಹೊಂಗಿರಣ'",
            "feature": "ಪುಸ್ತಕ ಪರಿಚಯ",
            "text": "ಮೈಸೂರಿನ ಪದವಿ ಪೂರ್ವ ಕಾಲೇಜೊಂದರೆಲ್ಲಿ ಉಪನ್ಯಾಸಕರಾಗಿರುವ",
            "page": "0032-0032"
        },
        {
            "title": "ಭಗವತ್ಪ್ರೇಮಮಯ  ನಾರಿ ಮೀರಾಬಾಯಿ",
            "feature": "ಸಂತರ ಜೀವನ ಕಥೆ",
            "text": "ಪ್ರಕೃತಿಯಲ್ಲೆಲ್ಲ ನಾವು ಪ್ರೇಮದ ಪ್ರಭಾವವನ್ನು ನೋಡುತ್ತಿದ್ದೇವೆ",
            "page": "0033-0037",
            "author": [
                {
                    "name": "ವೀರೇಶಾನಂದ",
                    "salutation": "ಸ್ವಾಮಿ "
                }
            ]
        },
        {
            "title": "ಸೋದರಿ ನಿವೇದಿತಾ",
            "feature": "ಚಿತ್ರಕಥೆ",
            "text": "ಸ್ವಾಮಿ ವಿವೇಕಾನಂದರ ವಿದೇಶೀ ಶಿಷ್ಯರುಗಳಲ್ಲಿ ಶ್ರೇಷ್ಠರಾದವರೇ ಸೋದರಿ ವಿವೇದಿತಾ",
            "page": "0038-0041"
        }
    ]
}