{
    "volume": "006",
    "issue": "07",
    "year": "2005",
    "month": "07",
    "theme": "",
    "id": "006/07",
    "toc": [
        {
            "title": "ರಾಮಕೃಷ್ಣ ಮಹಾಸಂಘದ ನೂತನ ಪರಮಾಧ್ಯಕ್ಷರು",
            "feature": "",
            "page": "0003-0004",
            "fullText": [
                {
                    "page": "0003",
                    "text": ""
                },
                {
                    "page": "0004",
                    "text": ""
                }
            ],
            "relativePageNumber": 2,
            "author": [
                {
                    "name": "ಸಂಪಾದಕರು",
                    "salutation": ""
                }
            ]
        },
        {
            "title": "ಪ್ರಾರ್ಥನೆ",
            "feature": "ಪ್ರಾರ್ಥನೆ",
            "page": "0007-0007",
            "fullText": [
                {
                    "page": "0007",
                    "text": ""
                }
            ],
            "relativePageNumber": 6,
            "author": [
                {
                    "name": "ಸಂಪಾದಕರು",
                    "salutation": ""
                }
            ]
        },
        {
            "title": "ಕಾರ್ಯನಿರ್ವಹಣೆ -೧",
            "feature": "ಸಂಪಾದಕರು",
            "page": "0009-0012",
            "fullText": [
                {
                    "page": "0009",
                    "text": ""
                },
                {
                    "page": "0010",
                    "text": ""
                },
                {
                    "page": "0011",
                    "text": ""
                },
                {
                    "page": "0012",
                    "text": ""
                }
            ],
            "relativePageNumber": 8,
            "author": [
                {
                    "name": "ಸಂಪಾದಕರು",
                    "salutation": ""
                }
            ]
        },
        {
            "title": "ಮಹತ್ತಿನ ಸನ್ನಿಧಿಯಲ್ಲಿ",
            "feature": "",
            "page": "0013-0018",
            "fullText": [
                {
                    "page": "0013",
                    "text": ""
                },
                {
                    "page": "0014",
                    "text": ""
                },
                {
                    "page": "0015",
                    "text": ""
                },
                {
                    "page": "0016",
                    "text": ""
                },
                {
                    "page": "0017",
                    "text": ""
                },
                {
                    "page": "0018",
                    "text": ""
                }
            ],
            "relativePageNumber": 12,
            "author": [
                {
                    "name": "ಭಜನಾನಂದ",
                    "salutation": "ಸ್ವಾಮಿ "
                }
            ]
        },
        {
            "title": "ಪ್ರಹಸನ ಪ್ರಸಂಗ",
            "feature": "ಪ್ರಹಸನ ಪ್ರಸಂಗ /ಆಧ್ಯಾತ್ಮಿಕ ಪ್ರಹಸನ",
            "page": "0019-0019",
            "fullText": [
                {
                    "page": "0019",
                    "text": ""
                }
            ],
            "relativePageNumber": 18,
            "author": [
                {
                    "name": "ಸಂಪಾದಕರು",
                    "salutation": ""
                }
            ]
        },
        {
            "title": "ಶ್ರೀರಾಮಕೃಷ್ಣ ಅವತಾರದ ವೈಶಿಷ್ಟ್ಯ",
            "feature": "",
            "page": "0020-0023",
            "fullText": [
                {
                    "page": "0020",
                    "text": ""
                },
                {
                    "page": "0021",
                    "text": ""
                },
                {
                    "page": "0022",
                    "text": ""
                },
                {
                    "page": "0023",
                    "text": ""
                }
            ],
            "relativePageNumber": 19,
            "author": [
                {
                    "name": "ಆತ್ಮವಿದಾನಂದ",
                    "salutation": "ಸ್ವಾಮಿ "
                }
            ]
        },
        {
            "title": "ಸ್ವಾಮಿ ರಂಗನಾಥಾನಂದರೊಡನೆ ಕೆಲವು ರಸನಿಮಿಷಗಳು",
            "feature": "",
            "page": "0024-0026",
            "fullText": [
                {
                    "page": "0024",
                    "text": ""
                },
                {
                    "page": "0025",
                    "text": ""
                },
                {
                    "page": "0026",
                    "text": ""
                }
            ],
            "relativePageNumber": 23,
            "author": [
                {
                    "name": "ಕೃಷ್ಣಸ್ವಾಮಿ ಪ್ರೊ. ಎನ್.",
                    "salutation": ""
                }
            ]
        },
        {
            "title": "ಶ್ರೀರಾಮಾನುಜರ ಜೀವನ ಮತ್ತು ಸಾಧನೆ -೩",
            "feature": "",
            "page": "0027-0029",
            "fullText": [
                {
                    "page": "0027",
                    "text": ""
                },
                {
                    "page": "0028",
                    "text": ""
                },
                {
                    "page": "0029",
                    "text": ""
                }
            ],
            "relativePageNumber": 26,
            "author": [
                {
                    "name": "ತಪಸ್ಯಾನಂದ",
                    "salutation": "ಸ್ವಾಮಿ "
                }
            ]
        },
        {
            "title": "ಗುರುಪೂರ್ಣಿಮಾ-ಗುರು ರಾಮಕೃಷ್ಣ",
            "feature": "",
            "page": "0030-0033",
            "fullText": [
                {
                    "page": "0030",
                    "text": ""
                },
                {
                    "page": "0031",
                    "text": ""
                },
                {
                    "page": "0032",
                    "text": ""
                },
                {
                    "page": "0033",
                    "text": ""
                }
            ],
            "relativePageNumber": 29,
            "author": [
                {
                    "name": "ರಾಘವೇಶಾನಂದ",
                    "salutation": "ಸ್ವಾಮಿ "
                }
            ]
        },
        {
            "title": "ಶ್ರೀರಾಮಕೃಷ್ಣ ಮಹಿಮಾ",
            "feature": "",
            "page": "0034-0034",
            "fullText": [
                {
                    "page": "0034",
                    "text": ""
                }
            ],
            "relativePageNumber": 33,
            "author": [
                {
                    "name": "ಸಂಪಾದಕರು",
                    "salutation": ""
                }
            ]
        },
        {
            "title": "ಬಡವರ ಸಂಜೀವಿನಿಯಾಗಿ ಡಾ. ಸಂಜೀವಿ",
            "feature": "ಯುವವೇದಿಕೆ",
            "page": "0035-0037",
            "fullText": [
                {
                    "page": "0035",
                    "text": ""
                },
                {
                    "page": "0036",
                    "text": ""
                },
                {
                    "page": "0037",
                    "text": ""
                }
            ],
            "relativePageNumber": 34,
            "author": [
                {
                    "name": "ಬಸವಲಿಂಗಪ್ಪ ಶಿವನಕೆರೆ",
                    "salutation": ""
                }
            ]
        },
        {
            "title": "ಕೇಳಿ ತಿಳಿಯಿರಿ",
            "feature": "ಕೇಳಿ ತಿಳಿಯಿರಿ",
            "page": "0037-0037",
            "fullText": [
                {
                    "page": "0037",
                    "text": ""
                }
            ],
            "relativePageNumber": 36,
            "author": [
                {
                    "name": "ಸಂಪಾದಕರು",
                    "salutation": ""
                }
            ]
        },
        {
            "title": "ವಾರ್ತಾ ವಿಶ್ಲೇಷಣೆ- ಅಂಗವಿಕಲರಿಗಾಗುವ ಅಪಮಾನ- ಗ್ರಾಮೀಣ ವಿದ್ಯಾರ್ಥಿಗಳ ವಿಜಯಸಾಧನೆ",
            "feature": "ವಾರ್ತಾವಿಶ್ಲೇಷಣೆ",
            "page": "0038-0038",
            "fullText": [
                {
                    "page": "0038",
                    "text": ""
                }
            ],
            "relativePageNumber": 37,
            "author": [
                {
                    "name": "ಸಂಪಾದಕರು",
                    "salutation": ""
                }
            ]
        },
        {
            "title": "ಸ್ನೇಹದ ಹಸ್ತ",
            "feature": "ಕಥೋಪದೇಶ",
            "page": "0039-0039",
            "fullText": [
                {
                    "page": "0039",
                    "text": ""
                }
            ],
            "relativePageNumber": 38,
            "author": [
                {
                    "name": "ಸಂಪಾದಕರು",
                    "salutation": ""
                }
            ]
        },
        {
            "title": "ಬೆವರಿನ ದುಡಿಮೆ",
            "feature": "",
            "page": "0040-0040",
            "fullText": [
                {
                    "page": "0040",
                    "text": ""
                }
            ],
            "relativePageNumber": 39,
            "author": [
                {
                    "name": "ಸಂಪಾದಕರು",
                    "salutation": ""
                }
            ]
        },
        {
            "title": "ಸುದ್ದಿ ಸಂಚಯ",
            "feature": "ಸುದ್ದಿಸಂಚಯ",
            "page": "0041-0041",
            "fullText": [
                {
                    "page": "0041",
                    "text": ""
                }
            ],
            "relativePageNumber": 40,
            "author": [
                {
                    "name": "ಸಂಪಾದಕರು",
                    "salutation": ""
                }
            ]
        }
    ]
}