{
    "volume": "016",
    "issue": "07",
    "month": "07",
    "year": "2015",
    "theme": "",
    "id": "016/07",
    "toc": [
        {
            "title": "ಪ್ರಾರ್ಥನೆ - ಗುರೂಪಸತ್ತಿ ಸೂಕ್ತಿಪ್ರಭ - ವೇಮನನ ಸೂಕ್ತಿಗಳು",
            "feature": "ಪ್ರಾರ್ಥನೆ",
            "text": "",
            "page": "0005-0005"
        },
        {
            "title": "ಧರ್ಮ ಮತ್ತು ಶ್ರದ್ಧೆ",
            "feature": "ಸಂಪಾದಕೀಯ",
            "text": "",
            "page": "0007-0010"
        },
        {
            "title": "ಗುರುಕೃಪೆ",
            "feature": "ವಿಶೇಷ ಲೇಖನ",
            "text": "ಈ ಹೆಸರು ಸಾಧಕನ ಮನಸ್ಸಿನಲ್ಲಿ ಒಮ್ಮೆಲೆ ತಂದೆಯಲ್ಲಿನ ರಕ್ಷಣೆ",
            "page": "0011-0014",
            "author": [
                {
                    "name": "ಕರುಣಾಕರಾನಂದ",
                    "salutation": "ಸ್ವಾಮಿ "
                }
            ]
        },
        {
            "title": "ಸ್ವಾಮಿ ಅಖಂಡಾನಂದರ ಸ್ಮೃತಿಸಂಚಯ - ಭಾಗ ೯",
            "feature": "ಧಾರಾವಾಹಿ",
            "text": "ಬಾಬಾ ಹೇಳತೊಡಗಿದರು ೧೪ ವರ್ಷಗಳ ಕಾಲ ನನಗೆ ಹಣದ ಸ್ಪರ್ಶವೇ ಇರಲಿಲ್ಲ. ಗಿರಿ, ವನಗಳಲ್ಲಿ ಸಂಚರಿಸುತ್ತಿದ್ದಾಗ ಒಂದೇ",
            "page": "0015-0017",
            "author": [
                {
                    "name": "ನಿರಾಮಯಾನಂದ",
                    "salutation": "ಸ್ವಾಮಿ"
                }
            ]
        },
        {
            "title": "ಕೈಲಾಸ-ಮಾನಸ ಸರೋವರ ಯಾತ್ರೆ - ಭಾಗ ೨",
            "feature": "ಧಾರಾವಾಹಿ",
            "text": "ಲ್ಹಾಸಾದಲ್ಲಿದ್ದುಕೊಂಡು ದಲೈಲಾಮಾ ಅವರು ಟಿಬೆಟ್ ದೇಶವನ್ನು ಆಲುತ್ತಿದ್ದರು",
            "page": "0018-0020",
            "author": [
                {
                    "name": "ದಾಮೋದರಾನಂದ",
                    "salutation": "ಸ್ವಾಮಿ"
                }
            ]
        },
        {
            "title": "ಗುರುವಿನ ಆದರ್ಶ ಮತ್ತು ಆಧುನಿಕ ಶಿಕ್ಷಣ",
            "feature": "ವಿಶೇಷ ಲೇಖನ",
            "text": "ಶಿಕ್ಷಣ ಎಂದೊಡನೆ ಮೊದಲು ನಮ್ಮ ಗಮನಕ್ಕೆ ಬರುವುದು ಗುರು-ಶಿಷ್ಯ ಸಂಬಂಧ",
            "page": "0021-0025",
            "author": [
                {
                    "name": "ರಾಜೇಂದ್ರ.ಡಿ.ಕೆ.",
                    "salutation": "ಡಾ"
                }
            ]
        },
        {
            "title": "ಕ್ಷೇತ್ರ ಮತ್ತು ಕ್ಷೇತ್ರಜ್ಞ",
            "feature": "ಭಗವದ್ಗೀತಾ ತತ್ತ್ವ ಸೌರಭ",
            "text": "ಸಾಮಾನ್ಯವಾಗಿ ನಮ್ಮ ಗಮನವೆಲ್ಲ ಹೊರಮುಖವಾಗಿರುತ್ತದೆ ಹೊರಜಗತ್ತು ನಮಗೆ",
            "page": "0026-0029",
            "author": [
                {
                    "name": "ನಿತ್ಯಸ್ಥಾನಂದ",
                    "salutation": "ಸ್ವಾಮಿ "
                }
            ]
        },
        {
            "title": "ಸಚ್ಚಿದಾನಂದನೇ ಗುರು",
            "feature": "ಶ್ರೀರಾಮಕೃಷ್ಣ ವಚನವೇದದಿಂದ",
            "text": "ಎಲ್ಲರಿಗೂ ಮುಕ್ತಿ ದೊರೆಯುತ್ತದೆ. ಆದರೆ ಗುರುವಿನ ಉಪದೇಶಕ್ಕನುಸಾರ ನಡೆದುಕೊಳ್ಳಬೇಕು",
            "page": "0030-0030"
        },
        {
            "title": "ಸ್ವಾಮಿ ಭೂತೇಶಾನಂದಜಿಯವರೊಂದಿಗೆ",
            "feature": "ಆಧ್ಯಾತ್ಮಿಕ ಸಂಭಾಷಣೆ",
            "text": "ಯಾರದು ಕೊನೆಯ ಜನ್ಮವೋ ಅವರು ಇಲ್ಲಿಗೆ ಬಂದೇ ತೀರಬೇಕು ಎಂದು ಶ್ರೀರಾಮಕೃಷ್ಣರು ಹೇಳುತ್ತಾರೆ",
            "page": "0031-0033"
        },
        {
            "title": "ಇಂದ್ರ ಮತ್ತು ಅಹಲ್ಯೆಯ ಕಥೆ",
            "feature": "ಯೋಗವಾಸಿಷ್ಠದ ಕಥೆಗಳು",
            "text": "ವಸಿಷ್ಠರು ರಾಮಚಂದ್ರನಿಗೆ ಉಪದೇಶ ಮಾಡುತ್ತಿದ್ದಾರೆ",
            "page": "0034-0036",
            "author": [
                {
                    "name": "ವೀರೇಶಾನಂದ",
                    "salutation": "ಸ್ವಾಮಿ "
                }
            ]
        },
        {
            "title": "ಗುರುದಕ್ಷಿಣೆ",
            "feature": "ಚಿತ್ರಕಥೆ",
            "text": "ವರತಂತು ಋಷಿಗಳ ಗುರುಕುಲದಲ್ಲಿ ಹಲವು ಮಂದಿ ಶಿಷ್ಯಂದಿರು ವಿದ್ಯಾಭ್ಯಾಸ ಮಾಡುತ್ತಿದ್ದರು",
            "page": "0037-0040"
        },
        {
            "title": "ಸುದ್ದಿ ಸಂಚಯ",
            "feature": "",
            "text": "",
            "page": "0041-0042"
        }
    ]
}