{
    "volume": "014",
    "issue": "06",
    "month": "06",
    "year": "2013",
    "theme": "",
    "id": "014/06",
    "toc": [
        {
            "title": "ಪ್ರಾರ್ಥನೆ, ಸೂಕ್ತಿಪ್ರಭ",
            "feature": "",
            "text": "",
            "page": "0005-0005"
        },
        {
            "title": "ಆಧುನಿಕ ಕಾಲದಲ್ಲಿ ಧ್ಯಾನಾಭ್ಯಾಸ",
            "feature": "ಸಂಪಾದಕೀಯ",
            "text": "",
            "page": "0007-0009"
        },
        {
            "title": "ರಸಬೋಧೆ",
            "feature": "",
            "text": "",
            "page": "0010-0010",
            "author": [
                {
                    "name": "ಭೂತೇಶಾನಂದ",
                    "salutation": "ಸ್ವಾಮಿ "
                }
            ]
        },
        {
            "title": "ಸ್ತೋತ್ರಪಠನ ದರ್ಶನ",
            "feature": "",
            "text": "",
            "page": "0011-0011",
            "author": [
                {
                    "name": "ಹರ್ಷಾನಂದ",
                    "salutation": "ಸ್ವಾಮಿ "
                }
            ]
        },
        {
            "title": "ಪವಿತ್ರ ಪತ್ರಮಾಲೆ: ಸ್ವಾಮಿ ತುರೀಯಾನಂದಜಿ ಅವರ ಒಂದು ಪತ್ರ",
            "feature": "",
            "text": "",
            "page": "0012-0012"
        },
        {
            "title": "ಭಗವದ್ಗೀತಾ ತತ್ತ್ವಸೌರಭ: ಜ್ಞಾನದ ಮಹಿಮೆ",
            "feature": "",
            "text": "",
            "page": "0013-0015",
            "author": [
                {
                    "name": "ನಿತ್ಯಸ್ಥಾನಂದ",
                    "salutation": "ಸ್ವಾಮಿ "
                }
            ]
        },
        {
            "title": "ಪೋಷಕರೇ ಗಮನಿಸಿ: ಮಕ್ಕಳಲ್ಲಿ ಬೆಳೆಸಬೇಕಾದ ಉತ್ತಮ ಹವ್ಯಾಸಗಳು",
            "feature": "",
            "text": "",
            "page": "0016-0016"
        },
        {
            "title": "ಪ್ರಾರ್ಥನೆಯ ಗುಣಾತ್ಮಕ ಪರಿಣಾಮಗಳು",
            "feature": "",
            "text": "",
            "page": "0017-0019",
            "author": [
                {
                    "name": "ಬಿ.ಎಮ್.ಎನ್.ಮೂರ್ತಿ",
                    "salutation": ""
                }
            ]
        },
        {
            "title": "ಶಿಕ್ಷಕರೇ ಗಮನಿಸಿ: ಮನಶ್ಯಾಸ್ತ್ರದ ವಿಧಾನಗಳು: ಆತ್ಮವಿಶ್ಲೇಷಣೆ",
            "feature": "",
            "text": "",
            "page": "0020-0020",
            "author": [
                {
                    "name": "ಎಸ್. ದಂಡಪಾಣಿ",
                    "salutation": "ಪ್ರೊ"
                }
            ]
        },
        {
            "title": "ಜಪದ ಮಹಿಮೆ",
            "feature": "",
            "text": "",
            "page": "0021-0024",
            "author": [
                {
                    "name": "ವಿಲಿಯಮ್ ಪೇಜ್",
                    "salutation": ""
                }
            ]
        },
        {
            "title": "ವಿದ್ಯಾರ್ಥಿಗಳೇ ಗಮನಿಸಿ: ಧಾರ್ಮಿಕ ಶಿಕ್ಷಣದ ಆವಶ್ಯಕತೆ",
            "feature": "",
            "text": "",
            "page": "0025-0025"
        },
        {
            "title": "ರಾಮಾನುಜರನ್ನು ಕುರಿತು ಸ್ವಾಮಿ ವಿವೇಕಾನಂದರು",
            "feature": "",
            "text": "",
            "page": "0026-0029",
            "author": [
                {
                    "name": "ಎಚ್. ರಾಮಚಂದ್ರಸ್ವಾಮಿ",
                    "salutation": "ಡಾ"
                }
            ]
        },
        {
            "title": "ಜೀವನಪ್ರಭ: ಒತ್ತಡ ನಿರ್ವಹಣೆಯ ಹಲವು ವಿಧಾನಗಳು",
            "feature": "",
            "text": "",
            "page": "0030-0030"
        },
        {
            "title": "ಶ್ರೀರಾಮನಾಮ ಸಂಕೀರ್ತನೆಯ ರೋಚಕ ಇತಿಹಾಸ",
            "feature": "",
            "text": "",
            "page": "0031-0033",
            "author": [
                {
                    "name": "ವಿದೇಹಾತ್ಮಾನಂದ",
                    "salutation": "ಸ್ವಾಮಿ"
                }
            ]
        },
        {
            "title": "ಶ್ರೀರಾಮಾನುಜರು - ಜೀವನ ಮತ್ತು ಸಾಧನೆ",
            "feature": "",
            "text": "",
            "page": "0034-0035",
            "author": [
                {
                    "name": "ಎಚ್.ವಿ.ಸರೋಜ",
                    "salutation": ""
                }
            ]
        },
        {
            "title": "ಛಾಯಾಚಿತ್ರಗಳಲ್ಲಿ ಸ್ವಾಮಿ ವಿವೇಕಾನಂದರು",
            "feature": "",
            "text": "",
            "page": "0036-0037",
            "author": [
                {
                    "name": "ಕೆ. ಆರ್. ಮೋಹನ್",
                    "salutation": ""
                }
            ]
        },
        {
            "title": "ಚಿತ್ರಕಥೆ: ನಾರಾಯಣ ತೀರ್ಥ",
            "feature": "",
            "text": "",
            "page": "0038-0041"
        },
        {
            "title": "ಸುದ್ದಿ ಸಂಚಯ",
            "feature": "",
            "text": "",
            "page": "0042-0042"
        }
    ]
}