{
    "volume": "006",
    "issue": "05",
    "year": "2005",
    "month": "05",
    "theme": "",
    "id": "006/05",
    "toc": [
        {
            "title": "ಪ್ರಾರ್ಥನೆ",
            "feature": "ಪ್ರಾರ್ಥನೆ",
            "page": "0005-0005",
            "fullText": [
                {
                    "page": "0005",
                    "text": ""
                }
            ],
            "relativePageNumber": 4,
            "author": [
                {
                    "name": "ಸಂಪಾದಕರು",
                    "salutation": ""
                }
            ]
        },
        {
            "title": "ಕಾರ್ಯಪ್ರವೃತ್ತಿ",
            "feature": "ಸಂಪಾದಕರು",
            "page": "0007-0010",
            "fullText": [
                {
                    "page": "0007",
                    "text": ""
                },
                {
                    "page": "0008",
                    "text": ""
                },
                {
                    "page": "0009",
                    "text": ""
                },
                {
                    "page": "0010",
                    "text": ""
                }
            ],
            "relativePageNumber": 6,
            "author": [
                {
                    "name": "ಸಂಪಾದಕರು",
                    "salutation": ""
                }
            ]
        },
        {
            "title": "ಸರ್ವಭಾವಮಯ ಶ್ರೀರಾಮಕೃಷ್ಣ",
            "feature": "",
            "page": "0011-0014",
            "fullText": [
                {
                    "page": "0011",
                    "text": ""
                },
                {
                    "page": "0012",
                    "text": ""
                },
                {
                    "page": "0013",
                    "text": ""
                },
                {
                    "page": "0014",
                    "text": ""
                }
            ],
            "relativePageNumber": 10,
            "author": [
                {
                    "name": "ಭೂತೇಶಾನಂದ",
                    "salutation": "ಸ್ವಾಮಿ "
                }
            ]
        },
        {
            "title": "ಕರ್ನಾಟಕದಲ್ಲಿ ಶ್ರೀರಾಮಾನುಜರು",
            "feature": "",
            "page": "0015-0016",
            "fullText": [
                {
                    "page": "0015",
                    "text": ""
                },
                {
                    "page": "0016",
                    "text": ""
                }
            ],
            "relativePageNumber": 14,
            "author": [
                {
                    "name": "ರಾಮಕೃಷ್ಣಾನಂದ",
                    "salutation": "ಸ್ವಾಮಿ "
                }
            ]
        },
        {
            "title": "ಮಾನವ ಜನ್ಮದ ಹಿರಿಮೆ",
            "feature": "",
            "page": "0017-0018",
            "fullText": [
                {
                    "page": "0017",
                    "text": ""
                },
                {
                    "page": "0018",
                    "text": ""
                }
            ],
            "relativePageNumber": 16,
            "author": [
                {
                    "name": "ಚಂದ್ರಶೇಖರ ಭಾರತೀ ಸ್ವಾಮಿಗಳು",
                    "salutation": "ಶ್ರೀ "
                }
            ]
        },
        {
            "title": "ಸ್ವಾಮಿ ವಿವೇಕಾನಂದ ಮತ್ತು ಲಿಯೋ ಟಾಲ್ಸ್ಟಾಯ್- ಎರಡು ಸಮಕಾಲೀನ ಚಿಂತನಶಕ್ತಿಗಳು",
            "feature": "",
            "page": "0019-0022",
            "fullText": [
                {
                    "page": "0019",
                    "text": ""
                },
                {
                    "page": "0020",
                    "text": ""
                },
                {
                    "page": "0021",
                    "text": ""
                },
                {
                    "page": "0022",
                    "text": ""
                }
            ],
            "relativePageNumber": 18,
            "author": [
                {
                    "name": "ಅಭಯಚೈತನ್ಯ ಬ್ರ.",
                    "salutation": ""
                }
            ]
        },
        {
            "title": "ಶ್ರೀರಾಮಾನುಜರು - ಜೀವನ ಮತ್ತು ಸಾಧನೆ -೧",
            "feature": "",
            "page": "0023-0027",
            "fullText": [
                {
                    "page": "0023",
                    "text": ""
                },
                {
                    "page": "0024",
                    "text": ""
                },
                {
                    "page": "0025",
                    "text": ""
                },
                {
                    "page": "0026",
                    "text": ""
                },
                {
                    "page": "0027",
                    "text": ""
                }
            ],
            "relativePageNumber": 22,
            "author": [
                {
                    "name": "ತಪಸ್ಯಾನಂದ",
                    "salutation": "ಸ್ವಾಮಿ "
                }
            ]
        },
        {
            "title": "ಕರ್ನಾಟಕ ಸಂಗೀತದ ದಿಗ್ಗಜರು",
            "feature": "",
            "page": "0028-0032",
            "fullText": [
                {
                    "page": "0028",
                    "text": ""
                },
                {
                    "page": "0029",
                    "text": ""
                },
                {
                    "page": "0030",
                    "text": ""
                },
                {
                    "page": "0031",
                    "text": ""
                },
                {
                    "page": "0032",
                    "text": ""
                }
            ],
            "relativePageNumber": 27,
            "author": [
                {
                    "name": "ಸರಸ್ವತಿ ವಿಜಯನಾರಸಿಂಹ",
                    "salutation": ""
                }
            ]
        },
        {
            "title": "ಪ್ರಹಸನ ಪ್ರಸಂಗ",
            "feature": "ಪ್ರಹಸನ ಪ್ರಸಂಗ /ಆಧ್ಯಾತ್ಮಿಕ ಪ್ರಹಸನ",
            "page": "0032-0032",
            "fullText": [
                {
                    "page": "0032",
                    "text": ""
                }
            ],
            "relativePageNumber": 31,
            "author": [
                {
                    "name": "ಸಂಪಾದಕರು",
                    "salutation": ""
                }
            ]
        },
        {
            "title": "ಶ್ರೀರಾಮಕೃಷ್ಣ ಮಹಿಮಾ",
            "feature": "",
            "page": "0033-0033",
            "fullText": [
                {
                    "page": "0033",
                    "text": ""
                }
            ],
            "relativePageNumber": 32,
            "author": [
                {
                    "name": "ಸಂಪಾದಕರು",
                    "salutation": ""
                }
            ]
        },
        {
            "title": "ಉನ್ನತ ಜೀವನ- ವ್ಯಕ್ತಿತ್ವ ವಿಕಸನದ ಸಾಧನೆ -೨",
            "feature": "ಯುವವೇದಿಕೆ",
            "page": "0034-0036",
            "fullText": [
                {
                    "page": "0034",
                    "text": ""
                },
                {
                    "page": "0035",
                    "text": ""
                },
                {
                    "page": "0036",
                    "text": ""
                }
            ],
            "relativePageNumber": 33,
            "author": [
                {
                    "name": "ವಸಂತ ಕುಮಾರ ಡಾ. ಇ.",
                    "salutation": ""
                }
            ]
        },
        {
            "title": "ಕೇಳಿ ತಿಳಿಯಿರಿ",
            "feature": "ಕೇಳಿ ತಿಳಿಯಿರಿ",
            "page": "0036-0037",
            "fullText": [
                {
                    "page": "0036",
                    "text": ""
                },
                {
                    "page": "0037",
                    "text": ""
                }
            ],
            "relativePageNumber": 35,
            "author": [
                {
                    "name": "ಸಂಪಾದಕರು",
                    "salutation": ""
                }
            ]
        },
        {
            "title": "ವಾರ್ತಾ ವಿಶ್ಲೇಷಣೆ- ಪುರಸ್ಕಾರ ಆಕೆಯನ್ನು ಅರಸಿತು ಆರೋಗ್ಯಕ್ಕೆ ಮಾರಕವಾಗಿರುವ ಪರಿಸರ ಮಾಲಿನ್ಯ",
            "feature": "ವಾರ್ತಾವಿಶ್ಲೇಷಣೆ",
            "page": "0038-0038",
            "fullText": [
                {
                    "page": "0038",
                    "text": ""
                }
            ],
            "relativePageNumber": 37,
            "author": [
                {
                    "name": "ಸಂಪಾದಕರು",
                    "salutation": ""
                }
            ]
        },
        {
            "title": "ಬಹುಜನ ಹಿತಾಯ",
            "feature": "ಕಥೋಪದೇಶ",
            "page": "0039-0039",
            "fullText": [
                {
                    "page": "0039",
                    "text": ""
                }
            ],
            "relativePageNumber": 38,
            "author": [
                {
                    "name": "ಸಂಪಾದಕರು",
                    "salutation": ""
                }
            ]
        },
        {
            "title": "ಸುದ್ದಿ ಸಂಚಯ",
            "feature": "ಸುದ್ದಿಸಂಚಯ",
            "page": "0040-0041",
            "fullText": [
                {
                    "page": "0040",
                    "text": ""
                },
                {
                    "page": "0041",
                    "text": ""
                }
            ],
            "relativePageNumber": 39,
            "author": [
                {
                    "name": "ಸಂಪಾದಕರು",
                    "salutation": ""
                }
            ]
        }
    ]
}