{
    "volume": "010",
    "issue": "12",
    "month": "12",
    "year": "2009",
    "theme": "",
    "id": "010/12",
    "toc": [
        {
            "title": "ಪ್ರಾರ್ಥನೆ",
            "feature": "ಪ್ರಾರ್ಥನೆ",
            "text": "",
            "page": "0005-0005",
            "author": [
                {
                    "name": "ಸಂಪಾದಕರು",
                    "salutation": ""
                }
            ]
        },
        {
            "title": "ಶ್ರೀಮಾತೆಯವರ ಮಡಿಲಿನಲ್ಲಿ ಕುಳಿತು",
            "feature": "ಸಂಪಾದಕರು",
            "text": "",
            "page": "0007-0010",
            "author": [
                {
                    "name": "ಸಂಪಾದಕರು",
                    "salutation": ""
                }
            ]
        },
        {
            "title": "ಶ್ರೀಮಾತೆ ಮತ್ತು ಅವರ -ಖೂಕಿ",
            "feature": "",
            "text": "",
            "page": "0011-0015",
            "author": [
                {
                    "name": "ಪೂರ್ಣಾತ್ಮಾನಂದ",
                    "salutation": "ಸ್ವಾಮಿ "
                }
            ]
        },
        {
            "title": "ಈ ಜಗತ್ತನ್ನು ಗೆಲ್ಲುವುದು ಹೇಗೆ?",
            "feature": "",
            "text": "",
            "page": "0016-0018",
            "author": [
                {
                    "name": "ಮುರಳೀಧರ ಡಾ. ಹೆಚ್. ಎನ್.",
                    "salutation": ""
                }
            ]
        },
        {
            "title": "ಶೀಮಾತೆಯವರ ಭಾವಗಾಂಭೀರ್ಯ",
            "feature": "",
            "text": "",
            "page": "0019-0022",
            "author": [
                {
                    "name": "ತ್ಯಾಗಮಯೀ ಮಾತಾ",
                    "salutation": ""
                }
            ]
        },
        {
            "title": "ವಾರಾಣಸೀಪುರಪತಿಂ ಭಜ ವಿಶ್ವನಾಥಂ",
            "feature": "",
            "text": "",
            "page": "0023-0025",
            "author": [
                {
                    "name": "ಉಷಾ ಪಿ.",
                    "salutation": ""
                }
            ]
        },
        {
            "title": "ವೀರಭಕ್ತ ಗಿರೀಶ್ ಚಂದ್ರ ಘೋಷ್",
            "feature": "",
            "text": "",
            "page": "0026-0027",
            "author": [
                {
                    "name": "ಪರಮಪ್ರಾಣಾ ಪ್ರವ್ರಾಜಿಕಾ",
                    "salutation": ""
                }
            ]
        },
        {
            "title": "ಶ್ರೀಮಾತೆಯವರೊಡನೆ ಮಾತುಕತೆ",
            "feature": "ಶಾರದಾದೇವಿಯವರೊಡನೆ ಮಾತುಕತೆ",
            "text": "",
            "page": "0028-0028",
            "author": [
                {
                    "name": "ಸಂಪಾದಕರು",
                    "salutation": ""
                }
            ]
        },
        {
            "title": "ವಿದ್ಯಾಭ್ಯಾಸದ ಪಂಚಶೀಲಗಳು",
            "feature": "",
            "text": "",
            "page": "0029-0029",
            "author": [
                {
                    "name": "ಜಗದಾತ್ಮಾನಂದ",
                    "salutation": "ಸ್ವಾಮಿ "
                }
            ]
        },
        {
            "title": "ಬನ್ನಿ, ಬೇಲೂರು ಮಠಕ್ಕೆ",
            "feature": "",
            "text": "",
            "page": "0030-0031",
            "author": [
                {
                    "name": "ಸಂಪಾದಕರು",
                    "salutation": ""
                }
            ]
        },
        {
            "title": "ಕರ್ನಾಟಕದ ಆಧ್ಯಾತ್ಮಿಕ ಪರಂಪರೆ- ಸಿದ್ಧಪುರುಷ ಸಿದ್ಧಾರೂಢರು",
            "feature": "",
            "text": "",
            "page": "0032-0033",
            "author": [
                {
                    "name": "ಸರಸ್ವತಿ ವಿಜಯನಾರಸಿಂಹ",
                    "salutation": ""
                }
            ]
        },
        {
            "title": "ಕಥೋಪದೇಶ",
            "feature": "ಕಥೋಪದೇಶ",
            "text": "",
            "page": "0034-0034",
            "author": [
                {
                    "name": "ಸಂಪಾದಕರು",
                    "salutation": ""
                }
            ]
        },
        {
            "title": "ಸ್ನೇಹಪ್ರಭ",
            "feature": "",
            "text": "",
            "page": "0035-0035",
            "author": [
                {
                    "name": "ಸಂಪಾದಕರು",
                    "salutation": ""
                }
            ]
        },
        {
            "title": "ವಾರ್ತಾ ವಿಶ್ಲೇಷಣೆ",
            "feature": "ವಾರ್ತಾವಿಶ್ಲೇಷಣೆ",
            "text": "",
            "page": "0035-0035",
            "author": [
                {
                    "name": "ಸಂಪಾದಕರು",
                    "salutation": ""
                }
            ]
        },
        {
            "title": "ಸುದ್ದಿ ಸಂಚಯ",
            "feature": "ಸುದ್ದಿಸಂಚಯ",
            "text": "",
            "page": "0036-0039",
            "author": [
                {
                    "name": "ಸಂಪಾದಕರು",
                    "salutation": ""
                }
            ]
        },
        {
            "title": "ವಾರ್ಷಿಕ ವಿಷಯಸೂಚಿ",
            "feature": "",
            "text": "",
            "page": "0040-0042",
            "author": [
                {
                    "name": "ಸಂಪಾದಕರು",
                    "salutation": ""
                }
            ]
        }
    ]
}